telenotify/__init__.py
telenotify/main.py
telenotify-0.0.2.dist-info/METADATA
telenotify-0.0.2.dist-info/WHEEL
telenotify-0.0.2.dist-info/top_level.txt
telenotify-0.0.2.dist-info/RECORD
